mpose/__init__.py
mpose/config.yaml
mpose/mpose.py
mpose/transforms.py
mpose/utils.py
mpose-1.1.0.dist-info/METADATA
mpose-1.1.0.dist-info/WHEEL
mpose-1.1.0.dist-info/top_level.txt
mpose-1.1.0.dist-info/RECORD
