Metadata-Version: 2.1
Name: mpose
Version: 1.1.0
Summary: MPOSE2021: a Dataset for Short-time Pose-based Human Action Recognition
Home-page: https://pypi.org/project/mpose/
Author: Simone Angarano
Author-email: simone.angarano@polito.it
License: MIT
Platform: UNKNOWN
Requires-Dist: importlib-resources
Requires-Dist: matplotlib
Requires-Dist: numpy
Requires-Dist: pyyaml
Requires-Dist: tqdm
